README.md
setup.py
stockmanage_lib/__init__.py
stockmanage_lib/manager.py
stockmanage_lib.egg-info/PKG-INFO
stockmanage_lib.egg-info/SOURCES.txt
stockmanage_lib.egg-info/dependency_links.txt
stockmanage_lib.egg-info/requires.txt
stockmanage_lib.egg-info/top_level.txt