Metadata-Version: 2.4
Name: stockmanage-lib
Version: 0.1.0
Summary: A Django library for stock management with role-based access
Author: Neeraj Reddy
Author-email: pneerajreddy390@gmail.com
Classifier: Programming Language :: Python :: 3
Classifier: License :: OSI Approved :: MIT License
Classifier: Operating System :: OS Independent
Requires-Python: >=3.6
Requires-Dist: django>=3.0
Dynamic: author
Dynamic: author-email
Dynamic: classifier
Dynamic: description
Dynamic: description-content-type
Dynamic: requires-dist
Dynamic: requires-python
Dynamic: summary
